{
  "battleResult": {
    "cheating": true,
    "winner": -1,
    "starsCount": -1,
    "cheatedInformation": "Invalid client version",
    "finishFlow": null,
    "leftScoring": {},
    "rightScoring": {},
    "scoreDelta": 0,
    "poweredAttackers": [],
    "poweredDefenders": [],
    "achievementsResult": [],
    "battleResultLogData": null
  },
  "rawBattleResult": null,
  "updateCheatStats": {
    "@class": "br.com.aquiris.pepe.core.model.player.persisted.battle.cheat.PlayerCheatStats",
    "configVersion": 0,
    "identifier": "78e7626c-994f-4744-9115-16077f67a284",
    "lastModifiedOn": 1764690858852,
    "createdOn": 1764690858852,
    "typeName": "PlayerCheatStats",
    "typeVersion": 4,
    "deprecated": false,
    "version": 1,
    "playerId": "46ea8d7e-1600-4049-bbc8-d5f99fd8b869",
    "clientData": null,
    "numberOfBattles": 1,
    "numberOfCheatedBattles": 1,
    "numberOfPvpBattles": 0,
    "numberOfCheatedPvpBattles": 0,
    "numberOfPveBattles": 1,
    "numberOfCheatedPveBattles": 1,
    "numberOfAcmeBattles": 0,
    "numberOfCheatedAcmeBattles": 0,
    "numberOfArenaBattles": 0,
    "numberOfCheatedArenaBattles": 0,
    "numberOfAllianceWarsBattles": 0,
    "numberOfCheatedAllianceWarsBattles": 0,
    "numberOfEnduranceTowerBattles": 0,
    "numberOfCheatedEnduranceTowerBattles": 0,
    "numberOfAcmeAllianceBattles": 0,
    "numberOfCheatedAcmeAllianceBattles": 0
  },
  "historyUrl": null
}
